.gitattributes
.gitignore
GenAIassignment.md
LICENCSE.txt
README.md
pyproject.toml
.idea/.gitignore
.idea/misc.xml
.idea/modules.xml
.idea/my_private_github.iml
.idea/vcs.xml
.idea/inspectionProfiles/Project_Default.xml
.idea/inspectionProfiles/profiles_settings.xml
my_github_tests.egg-info/PKG-INFO
my_github_tests.egg-info/SOURCES.txt
my_github_tests.egg-info/dependency_links.txt
my_github_tests.egg-info/top_level.txt
my_private_github/__init__.py
my_private_github/QuantScreener/quant_screener/__init__.py
my_private_github/QuantScreener/quant_screener/create_universe_data.py
my_private_github/QuantScreener/quant_screener/run_sp_screener.py
my_private_github/QuantScreener/quant_screener/sp_screener.py
my_private_github/QuantScreener/resources/basket_screener/PBA EQ.xlsx
my_private_github/QuantScreener/resources/basket_screener/benchmarks_timeseries.csv
my_private_github/QuantScreener/resources/basket_screener/etf_universe.xlsx
my_private_github/QuantScreener/resources/basket_screener/fundamentals.csv
my_private_github/QuantScreener/resources/basket_screener/fundamentals_samples.csv
my_private_github/QuantScreener/resources/basket_screener/price_timeseries.csv
my_private_github/QuantScreener/resources/basket_screener/price_timeseries_samples.csv
my_private_github/QuantScreener/resources/basket_screener/sample_baskets_20241119_1045.xlsx
my_private_github/QuantScreener/resources/basket_screener/sample_baskets_20241119_1051.xlsx
my_private_github/QuantScreener/resources/basket_screener/sample_baskets_20241120_2238.xlsx
my_private_github/blpapi/__init__.py
my_private_github/blpapi/abstractsession.py
my_private_github/blpapi/auth.py
my_private_github/blpapi/blpapi3_64.dll
my_private_github/blpapi/chandle.py
my_private_github/blpapi/constant.py
my_private_github/blpapi/correlationid.py
my_private_github/blpapi/ctypesutils.py
my_private_github/blpapi/datatype.py
my_private_github/blpapi/datetime.py
my_private_github/blpapi/debug.py
my_private_github/blpapi/debug_environment.py
my_private_github/blpapi/diagnosticsutil.py
my_private_github/blpapi/element.py
my_private_github/blpapi/event.py
