Metadata-Version: 2.4
Name: my-github-tests
Version: 1.0.9
Summary: my github tests
Author-email: AA SS <your.email@example.com>
License: MIT
Project-URL: Homepage, https://github.com/ArturSepp/my_private_github
Project-URL: Repository, https://github.com/ArturSepp/my_private_github
Project-URL: Issues, https://github.com/ArturSepp/my_private_github/issues
Classifier: Development Status :: 3 - Alpha
Classifier: Intended Audience :: Developers
Classifier: Programming Language :: Python :: 3
Classifier: Programming Language :: Python :: 3.9
Classifier: Programming Language :: Python :: 3.10
Classifier: Programming Language :: Python :: 3.11
Classifier: Programming Language :: Python :: 3.12
Classifier: Programming Language :: Python :: 3.13
Requires-Python: >=3.9
